plouf.py
templates.py
utils.py
plouf/__init__.py
plouf/plouf.py
plouf/templates.py
plouf/utils.py
plouf-0.1.dist-info/DESCRIPTION.rst
plouf-0.1.dist-info/METADATA
plouf-0.1.dist-info/RECORD
plouf-0.1.dist-info/WHEEL
plouf-0.1.dist-info/entry_points.txt
plouf-0.1.dist-info/metadata.json
plouf-0.1.dist-info/top_level.txt
