Metadata-Version: 2.0
Name: plouf
Version: 0.1
Summary: Little CLI tools to manage projects.
Home-page: https://github.com/Mazrog/plouf
Author: Mazrog
Author-email: maxime.cabanal@outlook.fr
License: UNKNOWN
Platform: UNKNOWN
Requires-Dist: Click
